{"mean":{"confidence_interval":{"confidence_level":0.95,"lower_bound":79348.73120803048,"upper_bound":80869.26970746041},"point_estimate":80076.68243679586,"standard_error":389.235082303275},"median":{"confidence_interval":{"confidence_level":0.95,"lower_bound":77931.58756137479,"upper_bound":78440.17094017094},"point_estimate":78249.05731523379,"standard_error":124.41556226053858},"median_abs_dev":{"confidence_interval":{"confidence_level":0.95,"lower_bound":487.831829763991,"upper_bound":1145.5116267539563},"point_estimate":802.2987666474066,"standard_error":174.46810705050362},"slope":{"confidence_interval":{"confidence_level":0.95,"lower_bound":80264.35586937924,"upper_bound":82760.84023111161},"point_estimate":81489.08031055689,"standard_error":638.792171418473},"std_dev":{"confidence_interval":{"confidence_level":0.95,"lower_bound":3104.265280900534,"upper_bound":4557.39616986534},"point_estimate":3920.5726038779076,"standard_error":370.50964052913287}}