{"mean":{"confidence_interval":{"confidence_level":0.95,"lower_bound":6528.921914981624,"upper_bound":6878.45568588108},"point_estimate":6704.118403756715,"standard_error":89.06178756204287},"median":{"confidence_interval":{"confidence_level":0.95,"lower_bound":6677.147474152918,"upper_bound":7165.277777777777},"point_estimate":7027.03320802005,"standard_error":118.55763423046359},"median_abs_dev":{"confidence_interval":{"confidence_level":0.95,"lower_bound":441.28095707797735,"upper_bound":1004.3077836053772},"point_estimate":671.0042984321199,"standard_error":139.2970644543731},"slope":{"confidence_interval":{"confidence_level":0.95,"lower_bound":6488.319928405386,"upper_bound":6961.239638762161},"point_estimate":6730.0312610994015,"standard_error":120.58253687121807},"std_dev":{"confidence_interval":{"confidence_level":0.95,"lower_bound":778.1310252005737,"upper_bound":999.8764676504095},"point_estimate":894.193273354545,"standard_error":56.41973225341028}}