{"mean":{"confidence_interval":{"confidence_level":0.95,"lower_bound":651503.6710671477,"upper_bound":654210.6771284781},"point_estimate":652763.5069863772,"standard_error":693.6294687496412},"median":{"confidence_interval":{"confidence_level":0.95,"lower_bound":650369.1310541311,"upper_bound":653648.4690799396},"point_estimate":651043.5555555555,"standard_error":938.4588993714556},"median_abs_dev":{"confidence_interval":{"confidence_level":0.95,"lower_bound":1199.9936094650125,"upper_bound":4627.194517850876},"point_estimate":2536.2934441022326,"standard_error":833.387106104437},"slope":{"confidence_interval":{"confidence_level":0.95,"lower_bound":652156.8258367126,"upper_bound":655638.1326190032},"point_estimate":653759.7321589882,"standard_error":906.1882028053219},"std_dev":{"confidence_interval":{"confidence_level":0.95,"lower_bound":2368.247574854521,"upper_bound":5824.853683902815},"point_estimate":4440.4060607933,"standard_error":846.8589621634125}}