{"mean":{"confidence_interval":{"confidence_level":0.95,"lower_bound":1741795.8616909327,"upper_bound":1789407.5702999658},"point_estimate":1765327.208444441,"standard_error":12124.963676145573},"median":{"confidence_interval":{"confidence_level":0.95,"lower_bound":1715144.0,"upper_bound":1796109.5238095238},"point_estimate":1760485.625,"standard_error":18140.877735232007},"median_abs_dev":{"confidence_interval":{"confidence_level":0.95,"lower_bound":116358.30040897433,"upper_bound":181110.90580637773},"point_estimate":149790.58040046826,"standard_error":16400.070658123},"slope":{"confidence_interval":{"confidence_level":0.95,"lower_bound":1695813.8554614217,"upper_bound":1753229.803815496},"point_estimate":1722643.3583567312,"standard_error":14672.806614673136},"std_dev":{"confidence_interval":{"confidence_level":0.95,"lower_bound":107580.82762537929,"upper_bound":134629.25580080762},"point_estimate":121908.50953304695,"standard_error":6897.439918780164}}